Workbook

Sheet INDEX
A1: RB/01 ÁLADÍN — MODELO DE PRECIOS POR CUPO · v1
A2: 2026-07-16 · Fuente de decisión para las compuertas §12 de GTM-CAMPAIGN.md
A4: CÓMO USAR | B4: Edita solo las celdas amarillas (hoja INPUTS y tarifas en FLETE). Todo lo demás son fórmulas.
A6: DECISIONES QUE SALEN DE ESTE LIBRO
A7: 1 · Markup base Wings | B7: INPUTS C33 — define el precio de cupo publicado (compuerta G3 del programa).
A8: 2 · Escalera [A]/[B]/desc. contenedor/[C] | B8: INPUTS C34–C37 — ratificar tras ver márgenes en hoja ESCALERA.
A9: 3 · EXW Tacna vs entregado | B9: Hoja FLETE — el flete por pack es 1.5–5% del precio público.
A10: 4 · Template facial | B10: Cajas/cupo 118 es BORRADOR no ratificado. Con retail S/25 el margen del comprador es ajustado; el escenario retail S/35 (segundo grid en FACIAL) lo convierte en producto estrella.
A11: 5 · Contenedor mixto | B11: Hoja MIXTO — higiénico + facial en el mismo cupo; resuelve la rotación del facial. Composición se ajusta con «cajas higiénico por cupo».
A13: RECOMENDACIÓN PRELIMINAR (a validar con estos números)
A14: · Precio publicado: | B14: EXW Tacna, un solo número por cupo. El mayorista de provincia tiene su transportista; empaquetar flete nos obliga a tarificar el peor caso.
A15: · Cadenas (S1): | B15: cotizar ENTREGADO a su CD — las cadenas no compran EXW. Dos segmentos, dos incoterms internos.
A16: · Punto de partida markup: | B16: 40% — el comprador conserva ~25% sobre venta en higiénico; argumento de venta claro y defendible.
A18: PREGUNTAS ABIERTAS (no las resuelve este libro)
A19: · Fiscal ZOFRATACNA/IGV: | B19: investigado 2026-07-16 — ver ZOFRATACNA.md en esta carpeta: la salida al resto del país es una importación (ad valorem + IGV/IPM 18% + percepción); dos estructuras posibles (Áladín nacionaliza vs comprador nacionaliza). Confirmar base del costo S/16 con agencia de aduana.
A20: · Ruta/hub: | B20: el contenedor seed dice Qingdao→Callao; el almacén principal es Tacna. Confirmar ruta real antes de fijar copy del instrumento.
A21: · Tarifas de flete: | B21: las de la hoja FLETE son PLACEHOLDERS — reemplazar con cotizaciones de transportista antes de publicar estimados.

Sheet INPUTS
A1: DRIVERS — todas las celdas amarillas son editables
A4: GENERAL
A5: Tipo de cambio (S/ por USD) | C5: 3.75
A6: IGV referencial | C6: 0.18
A8: PAPEL HIGIÉNICO — pack ×10 rollos
A9: Costo por pack, almacén Tacna (S/) | C9: 16
A10: Precio público objetivo por pack (S/) | C10: 30
A11: Spread total por pack (S/) | C11: =C10-C9 -> 14
A12: Packs por caja máster | C12: 6
A13: Cajas por cupo | C13: 94
A14: Cupos por contenedor (40HC) | C14: 10
A15: Packs por cupo | C15: =C12*C13 -> 564
A16: Cajas comerciales por contenedor | C16: =C13*C14 -> 940
A17: Cajas de holgura (stock propio) | C17: 5
A18: m³ por caja | C18: 0.0777
A19: kg por caja | C19: 9.7
A21: PAPEL FACIAL — pack ×5 empaques (390 hojas)
A22: Costo por pack ×5, almacén Tacna (S/) | C22: 14
A23: Precio público objetivo por pack ×5 (S/) | C23: 25
A24: Spread total por pack (S/) | C24: =C23-C22 -> 11
A25: Packs (×5) por caja máster | C25: 9
A26: Cajas por cupo | C26: 118
A27: Cupos por contenedor | C27: 10
A28: Packs por cupo | C28: =C25*C26 -> 1062
A29: m³ por caja | C29: 0.059
A30: kg por caja | C30: 9.7
A31: Precio público facial — escenario alto (S/) | C31: 35
A32: ESCALERA (GTM §2.2) — drivers de decisión
A33: Escenario base — markup Wings sobre costo | C33: 0.4 | D33: el dial principal: define el precio publicado
A34: [A] Descuento CUPO×3 (2–3 cupos) | C34: 0.03
A35: [B] Descuento MEDIO (5 cupos) | C35: 0.06
A36: Descuento CONTENEDOR (10 cupos) | C36: 0.08
A37: [C] Crédito padrino (s/ 1 cupo, ciclo siguiente) | C37: 0.02
A39: NOTA FISCAL (investigado 2026-07-16, ver ZOFRATACNA.md): la salida de mercancía NO producida en zona
A40: hacia el resto del país es una importación: ad valorem (banda probable 6%; TLC China puede dar 0% con
A41: certificado de origen) + IGV+IPM 18% + percepción. Confirmar con agencia de aduana la base del costo S/16.
A42: NOTA DE DATOS: costos vigentes declarados por Muaaz 2026-07-16; sustituyen el costeo SPSA 2020 (muerto).

Sheet HIGIENICO
A1: PAPEL HIGIÉNICO — escenarios de precio de cupo
A2: Costo y precio público en INPUTS ($C$9 / $C$10); cambiarlos allí recalcula todo.
A4: Markup s/ costo | B4: Precio S/ /pack | C4: Margen Wings S/ /pack | D4: Margen Wings % s/ precio | E4: Precio por cupo (S/) | F4: Precio por cupo (USD) | G4: Margen comprador S/ /pack | H4: Margen comprador % s/ venta | I4: Markup comprador s/ su costo | J4: Ganancia comprador por cupo (S/) | K4: Margen Wings por cupo (S/) | L4: Margen Wings por contenedor (S/)
A5: 0.3 | B5: =INPUTS!$C$9*(1+$A5) -> 20.8 | C5: =B5-INPUTS!$C$9 -> 4.8 | D5: =C5/B5 -> 0.23076923 | E5: =B5*INPUTS!$C$15 -> 11731.2 | F5: =E5/INPUTS!$C$5 -> 3128.32 | G5: =INPUTS!$C$10-B5 -> 9.2 | H5: =G5/INPUTS!$C$10 -> 0.30666667 | I5: =G5/B5 -> 0.44230769 | J5: =G5*INPUTS!$C$15 -> 5188.8 | K5: =C5*INPUTS!$C$15 -> 2707.2 | L5: =K5*INPUTS!$C$14 -> 27072
A6: 0.35 | B6: =INPUTS!$C$9*(1+$A6) -> 21.6 | C6: =B6-INPUTS!$C$9 -> 5.6 | D6: =C6/B6 -> 0.25925926 | E6: =B6*INPUTS!$C$15 -> 12182.4 | F6: =E6/INPUTS!$C$5 -> 3248.64 | G6: =INPUTS!$C$10-B6 -> 8.4 | H6: =G6/INPUTS!$C$10 -> 0.28 | I6: =G6/B6 -> 0.38888889 | J6: =G6*INPUTS!$C$15 -> 4737.6 | K6: =C6*INPUTS!$C$15 -> 3158.4 | L6: =K6*INPUTS!$C$14 -> 31584
A7: 0.4 | B7: =INPUTS!$C$9*(1+$A7) -> 22.4 | C7: =B7-INPUTS!$C$9 -> 6.4 | D7: =C7/B7 -> 0.28571429 | E7: =B7*INPUTS!$C$15 -> 12633.6 | F7: =E7/INPUTS!$C$5 -> 3368.96 | G7: =INPUTS!$C$10-B7 -> 7.6 | H7: =G7/INPUTS!$C$10 -> 0.25333333 | I7: =G7/B7 -> 0.33928571 | J7: =G7*INPUTS!$C$15 -> 4286.4 | K7: =C7*INPUTS!$C$15 -> 3609.6 | L7: =K7*INPUTS!$C$14 -> 36096
A8: 0.45 | B8: =INPUTS!$C$9*(1+$A8) -> 23.2 | C8: =B8-INPUTS!$C$9 -> 7.2 | D8: =C8/B8 -> 0.31034483 | E8: =B8*INPUTS!$C$15 -> 13084.8 | F8: =E8/INPUTS!$C$5 -> 3489.28 | G8: =INPUTS!$C$10-B8 -> 6.8 | H8: =G8/INPUTS!$C$10 -> 0.22666667 | I8: =G8/B8 -> 0.29310345 | J8: =G8*INPUTS!$C$15 -> 3835.2 | K8: =C8*INPUTS!$C$15 -> 4060.8 | L8: =K8*INPUTS!$C$14 -> 40608
A9: 0.5 | B9: =INPUTS!$C$9*(1+$A9) -> 24 | C9: =B9-INPUTS!$C$9 -> 8 | D9: =C9/B9 -> 0.33333333 | E9: =B9*INPUTS!$C$15 -> 13536 | F9: =E9/INPUTS!$C$5 -> 3609.6 | G9: =INPUTS!$C$10-B9 -> 6 | H9: =G9/INPUTS!$C$10 -> 0.2 | I9: =G9/B9 -> 0.25 | J9: =G9*INPUTS!$C$15 -> 3384 | K9: =C9*INPUTS!$C$15 -> 4512 | L9: =K9*INPUTS!$C$14 -> 45120
A10: =B10/INPUTS!$C$9-1 -> 0.4375 | B10: =INPUTS!$C$9+(INPUTS!$C$10-INPUTS!$C$9)/2 -> 23 | C10: =B10-INPUTS!$C$9 -> 7 | D10: =C10/B10 -> 0.30434783 | E10: =B10*INPUTS!$C$15 -> 12972 | F10: =E10/INPUTS!$C$5 -> 3459.2 | G10: =INPUTS!$C$10-B10 -> 7 | H10: =G10/INPUTS!$C$10 -> 0.23333333 | I10: =G10/B10 -> 0.30434783 | J10: =G10*INPUTS!$C$15 -> 3948 | K10: =C10*INPUTS!$C$15 -> 3948 | L10: =K10*INPUTS!$C$14 -> 39480 | M10: ← reparto igual del spread
A12: Convención alternativa: margen sobre PRECIO DE VENTA (precio = costo ÷ (1−margen))
A13: Margen s/ precio | B13: Precio S/ /pack | C13: Margen Wings S/ /pack | D13: Margen Wings % s/ precio | E13: Precio por cupo (S/) | F13: Precio por cupo (USD) | G13: Margen comprador S/ /pack | H13: Margen comprador % s/ venta | I13: Markup comprador s/ su costo | J13: Ganancia comprador por cupo (S/) | K13: Margen Wings por cupo (S/) | L13: Margen Wings por contenedor (S/)
A14: 0.3 | B14: =INPUTS!$C$9/(1-$A14) -> 22.857143 | C14: =B14-INPUTS!$C$9 -> 6.8571429 | D14: =C14/B14 -> 0.3 | E14: =B14*INPUTS!$C$15 -> 12891.429 | F14: =E14/INPUTS!$C$5 -> 3437.7143 | G14: =INPUTS!$C$10-B14 -> 7.1428571 | H14: =G14/INPUTS!$C$10 -> 0.23809524 | I14: =G14/B14 -> 0.3125 | J14: =G14*INPUTS!$C$15 -> 4028.5714 | K14: =C14*INPUTS!$C$15 -> 3867.4286 | L14: =K14*INPUTS!$C$14 -> 38674.286 | M14: =IF(B14>=INPUTS!$C$10,"⚠ supera el precio público — inviable","")
A15: 0.4 | B15: =INPUTS!$C$9/(1-$A15) -> 26.666667 | C15: =B15-INPUTS!$C$9 -> 10.666667 | D15: =C15/B15 -> 0.4 | E15: =B15*INPUTS!$C$15 -> 15040 | F15: =E15/INPUTS!$C$5 -> 4010.6667 | G15: =INPUTS!$C$10-B15 -> 3.3333333 | H15: =G15/INPUTS!$C$10 -> 0.11111111 | I15: =G15/B15 -> 0.125 | J15: =G15*INPUTS!$C$15 -> 1880 | K15: =C15*INPUTS!$C$15 -> 6016 | L15: =K15*INPUTS!$C$14 -> 60160 | M15: =IF(B15>=INPUTS!$C$10,"⚠ supera el precio público — inviable","")
A16: 0.5 | B16: =INPUTS!$C$9/(1-$A16) -> 32 | C16: =B16-INPUTS!$C$9 -> 16 | D16: =C16/B16 -> 0.5 | E16: =B16*INPUTS!$C$15 -> 18048 | F16: =E16/INPUTS!$C$5 -> 4812.8 | G16: =INPUTS!$C$10-B16 -> -2 | H16: =G16/INPUTS!$C$10 -> -0.066666667 | I16: =G16/B16 -> -0.0625 | J16: =G16*INPUTS!$C$15 -> -1128 | K16: =C16*INPUTS!$C$15 -> 9024 | L16: =K16*INPUTS!$C$14 -> 90240 | M16: =IF(B16>=INPUTS!$C$10,"⚠ supera el precio público — inviable","") -> ⚠ supera el precio público — inviable
A18: Rotación del comprador — semanas para vender 1 cupo
A19: Packs vendidos / semana | B19: 20 | C19: 40 | D19: 60 | E19: 100
A20: Semanas para rotar el cupo | B20: =INPUTS!$C$15/B19 -> 28.2 | C20: =INPUTS!$C$15/C19 -> 14.1 | D20: =INPUTS!$C$15/D19 -> 9.4 | E20: =INPUTS!$C$15/E19 -> 5.64

Sheet FACIAL
A1: PAPEL FACIAL — escenarios de precio de cupo (template BORRADOR)
A2: Costo y precio público en INPUTS ($C$22 / $C$23); cambiarlos allí recalcula todo.
A3: ⚠ Cajas/cupo = 118 no ratificado. Margen del comprador más ajustado que higiénico — ver columnas H–I.
A4: Markup s/ costo | B4: Precio S/ /pack | C4: Margen Wings S/ /pack | D4: Margen Wings % s/ precio | E4: Precio por cupo (S/) | F4: Precio por cupo (USD) | G4: Margen comprador S/ /pack | H4: Margen comprador % s/ venta | I4: Markup comprador s/ su costo | J4: Ganancia comprador por cupo (S/) | K4: Margen Wings por cupo (S/) | L4: Margen Wings por contenedor (S/)
A5: 0.3 | B5: =INPUTS!$C$22*(1+$A5) -> 18.2 | C5: =B5-INPUTS!$C$22 -> 4.2 | D5: =C5/B5 -> 0.23076923 | E5: =B5*INPUTS!$C$28 -> 19328.4 | F5: =E5/INPUTS!$C$5 -> 5154.24 | G5: =INPUTS!$C$23-B5 -> 6.8 | H5: =G5/INPUTS!$C$23 -> 0.272 | I5: =G5/B5 -> 0.37362637 | J5: =G5*INPUTS!$C$28 -> 7221.6 | K5: =C5*INPUTS!$C$28 -> 4460.4 | L5: =K5*INPUTS!$C$27 -> 44604
A6: 0.35 | B6: =INPUTS!$C$22*(1+$A6) -> 18.9 | C6: =B6-INPUTS!$C$22 -> 4.9 | D6: =C6/B6 -> 0.25925926 | E6: =B6*INPUTS!$C$28 -> 20071.8 | F6: =E6/INPUTS!$C$5 -> 5352.48 | G6: =INPUTS!$C$23-B6 -> 6.1 | H6: =G6/INPUTS!$C$23 -> 0.244 | I6: =G6/B6 -> 0.32275132 | J6: =G6*INPUTS!$C$28 -> 6478.2 | K6: =C6*INPUTS!$C$28 -> 5203.8 | L6: =K6*INPUTS!$C$27 -> 52038
A7: 0.4 | B7: =INPUTS!$C$22*(1+$A7) -> 19.6 | C7: =B7-INPUTS!$C$22 -> 5.6 | D7: =C7/B7 -> 0.28571429 | E7: =B7*INPUTS!$C$28 -> 20815.2 | F7: =E7/INPUTS!$C$5 -> 5550.72 | G7: =INPUTS!$C$23-B7 -> 5.4 | H7: =G7/INPUTS!$C$23 -> 0.216 | I7: =G7/B7 -> 0.2755102 | J7: =G7*INPUTS!$C$28 -> 5734.8 | K7: =C7*INPUTS!$C$28 -> 5947.2 | L7: =K7*INPUTS!$C$27 -> 59472
A8: 0.45 | B8: =INPUTS!$C$22*(1+$A8) -> 20.3 | C8: =B8-INPUTS!$C$22 -> 6.3 | D8: =C8/B8 -> 0.31034483 | E8: =B8*INPUTS!$C$28 -> 21558.6 | F8: =E8/INPUTS!$C$5 -> 5748.96 | G8: =INPUTS!$C$23-B8 -> 4.7 | H8: =G8/INPUTS!$C$23 -> 0.188 | I8: =G8/B8 -> 0.23152709 | J8: =G8*INPUTS!$C$28 -> 4991.4 | K8: =C8*INPUTS!$C$28 -> 6690.6 | L8: =K8*INPUTS!$C$27 -> 66906
A9: 0.5 | B9: =INPUTS!$C$22*(1+$A9) -> 21 | C9: =B9-INPUTS!$C$22 -> 7 | D9: =C9/B9 -> 0.33333333 | E9: =B9*INPUTS!$C$28 -> 22302 | F9: =E9/INPUTS!$C$5 -> 5947.2 | G9: =INPUTS!$C$23-B9 -> 4 | H9: =G9/INPUTS!$C$23 -> 0.16 | I9: =G9/B9 -> 0.19047619 | J9: =G9*INPUTS!$C$28 -> 4248 | K9: =C9*INPUTS!$C$28 -> 7434 | L9: =K9*INPUTS!$C$27 -> 74340
A10: =B10/INPUTS!$C$22-1 -> 0.39285714 | B10: =INPUTS!$C$22+(INPUTS!$C$23-INPUTS!$C$22)/2 -> 19.5 | C10: =B10-INPUTS!$C$22 -> 5.5 | D10: =C10/B10 -> 0.28205128 | E10: =B10*INPUTS!$C$28 -> 20709 | F10: =E10/INPUTS!$C$5 -> 5522.4 | G10: =INPUTS!$C$23-B10 -> 5.5 | H10: =G10/INPUTS!$C$23 -> 0.22 | I10: =G10/B10 -> 0.28205128 | J10: =G10*INPUTS!$C$28 -> 5841 | K10: =C10*INPUTS!$C$28 -> 5841 | L10: =K10*INPUTS!$C$27 -> 58410 | M10: ← reparto igual del spread
A12: Convención alternativa: margen sobre PRECIO DE VENTA (precio = costo ÷ (1−margen))
A13: Margen s/ precio | B13: Precio S/ /pack | C13: Margen Wings S/ /pack | D13: Margen Wings % s/ precio | E13: Precio por cupo (S/) | F13: Precio por cupo (USD) | G13: Margen comprador S/ /pack | H13: Margen comprador % s/ venta | I13: Markup comprador s/ su costo | J13: Ganancia comprador por cupo (S/) | K13: Margen Wings por cupo (S/) | L13: Margen Wings por contenedor (S/)
A14: 0.3 | B14: =INPUTS!$C$22/(1-$A14) -> 20 | C14: =B14-INPUTS!$C$22 -> 6 | D14: =C14/B14 -> 0.3 | E14: =B14*INPUTS!$C$28 -> 21240 | F14: =E14/INPUTS!$C$5 -> 5664 | G14: =INPUTS!$C$23-B14 -> 5 | H14: =G14/INPUTS!$C$23 -> 0.2 | I14: =G14/B14 -> 0.25 | J14: =G14*INPUTS!$C$28 -> 5310 | K14: =C14*INPUTS!$C$28 -> 6372 | L14: =K14*INPUTS!$C$27 -> 63720 | M14: =IF(B14>=INPUTS!$C$23,"⚠ supera el precio público — inviable","")
A15: 0.4 | B15: =INPUTS!$C$22/(1-$A15) -> 23.333333 | C15: =B15-INPUTS!$C$22 -> 9.3333333 | D15: =C15/B15 -> 0.4 | E15: =B15*INPUTS!$C$28 -> 24780 | F15: =E15/INPUTS!$C$5 -> 6608 | G15: =INPUTS!$C$23-B15 -> 1.6666667 | H15: =G15/INPUTS!$C$23 -> 0.066666667 | I15: =G15/B15 -> 0.071428571 | J15: =G15*INPUTS!$C$28 -> 1770 | K15: =C15*INPUTS!$C$28 -> 9912 | L15: =K15*INPUTS!$C$27 -> 99120 | M15: =IF(B15>=INPUTS!$C$23,"⚠ supera el precio público — inviable","")
A16: 0.5 | B16: =INPUTS!$C$22/(1-$A16) -> 28 | C16: =B16-INPUTS!$C$22 -> 14 | D16: =C16/B16 -> 0.5 | E16: =B16*INPUTS!$C$28 -> 29736 | F16: =E16/INPUTS!$C$5 -> 7929.6 | G16: =INPUTS!$C$23-B16 -> -3 | H16: =G16/INPUTS!$C$23 -> -0.12 | I16: =G16/B16 -> -0.10714286 | J16: =G16*INPUTS!$C$28 -> -3186 | K16: =C16*INPUTS!$C$28 -> 14868 | L16: =K16*INPUTS!$C$27 -> 148680 | M16: =IF(B16>=INPUTS!$C$23,"⚠ supera el precio público — inviable","") -> ⚠ supera el precio público — inviable
A18: Rotación del comprador — semanas para vender 1 cupo
A19: Packs vendidos / semana | B19: 20 | C19: 40 | D19: 60 | E19: 100
A20: Semanas para rotar el cupo | B20: =INPUTS!$C$28/B19 -> 53.1 | C20: =INPUTS!$C$28/C19 -> 26.55 | D20: =INPUTS!$C$28/D19 -> 17.7 | E20: =INPUTS!$C$28/E19 -> 10.62
A23: ESCENARIO RETAIL ALTO — precio público S/ 35 (INPUTS C31)
A24: Mismo costo S/14; solo cambia el precio de venta del comprador — su margen es la columna que se mueve.
A26: Markup s/ costo | B26: Precio S/ /pack | C26: Margen Wings S/ /pack | D26: Margen Wings % s/ precio | E26: Precio por cupo (S/) | F26: Precio por cupo (USD) | G26: Margen comprador S/ /pack | H26: Margen comprador % s/ venta | I26: Markup comprador s/ su costo | J26: Ganancia comprador por cupo (S/) | K26: Margen Wings por cupo (S/) | L26: Margen Wings por contenedor (S/)
A27: 0.3 | B27: =INPUTS!$C$22*(1+$A27) -> 18.2 | C27: =B27-INPUTS!$C$22 -> 4.2 | D27: =C27/B27 -> 0.23076923 | E27: =B27*INPUTS!$C$28 -> 19328.4 | F27: =E27/INPUTS!$C$5 -> 5154.24 | G27: =INPUTS!$C$31-B27 -> 16.8 | H27: =G27/INPUTS!$C$31 -> 0.48 | I27: =G27/B27 -> 0.92307692 | J27: =G27*INPUTS!$C$28 -> 17841.6 | K27: =C27*INPUTS!$C$28 -> 4460.4 | L27: =K27*INPUTS!$C$27 -> 44604 | M27: ← a S/35 retail el facial pasa de producto ajustado a producto estrella del comprador
A28: 0.35 | B28: =INPUTS!$C$22*(1+$A28) -> 18.9 | C28: =B28-INPUTS!$C$22 -> 4.9 | D28: =C28/B28 -> 0.25925926 | E28: =B28*INPUTS!$C$28 -> 20071.8 | F28: =E28/INPUTS!$C$5 -> 5352.48 | G28: =INPUTS!$C$31-B28 -> 16.1 | H28: =G28/INPUTS!$C$31 -> 0.46 | I28: =G28/B28 -> 0.85185185 | J28: =G28*INPUTS!$C$28 -> 17098.2 | K28: =C28*INPUTS!$C$28 -> 5203.8 | L28: =K28*INPUTS!$C$27 -> 52038
A29: 0.4 | B29: =INPUTS!$C$22*(1+$A29) -> 19.6 | C29: =B29-INPUTS!$C$22 -> 5.6 | D29: =C29/B29 -> 0.28571429 | E29: =B29*INPUTS!$C$28 -> 20815.2 | F29: =E29/INPUTS!$C$5 -> 5550.72 | G29: =INPUTS!$C$31-B29 -> 15.4 | H29: =G29/INPUTS!$C$31 -> 0.44 | I29: =G29/B29 -> 0.78571429 | J29: =G29*INPUTS!$C$28 -> 16354.8 | K29: =C29*INPUTS!$C$28 -> 5947.2 | L29: =K29*INPUTS!$C$27 -> 59472
A30: 0.45 | B30: =INPUTS!$C$22*(1+$A30) -> 20.3 | C30: =B30-INPUTS!$C$22 -> 6.3 | D30: =C30/B30 -> 0.31034483 | E30: =B30*INPUTS!$C$28 -> 21558.6 | F30: =E30/INPUTS!$C$5 -> 5748.96 | G30: =INPUTS!$C$31-B30 -> 14.7 | H30: =G30/INPUTS!$C$31 -> 0.42 | I30: =G30/B30 -> 0.72413793 | J30: =G30*INPUTS!$C$28 -> 15611.4 | K30: =C30*INPUTS!$C$28 -> 6690.6 | L30: =K30*INPUTS!$C$27 -> 66906
A31: 0.5 | B31: =INPUTS!$C$22*(1+$A31) -> 21 | C31: =B31-INPUTS!$C$22 -> 7 | D31: =C31/B31 -> 0.33333333 | E31: =B31*INPUTS!$C$28 -> 22302 | F31: =E31/INPUTS!$C$5 -> 5947.2 | G31: =INPUTS!$C$31-B31 -> 14 | H31: =G31/INPUTS!$C$31 -> 0.4 | I31: =G31/B31 -> 0.66666667 | J31: =G31*INPUTS!$C$28 -> 14868 | K31: =C31*INPUTS!$C$28 -> 7434 | L31: =K31*INPUTS!$C$27 -> 74340

Sheet MIXTO
A1: CONTENEDOR MIXTO 40HC — higiénico + facial en un mismo cupo
A2: ⚠ PROPUESTA — template no ratificado. La math del servidor (SPEC §3.2) manda; el factor de estiba mixta es supuesto hasta tener plan de carga real.
A4: GEOMETRÍA
A5: Volumen interior 40HC (m³) | C5: 76.4
A6: Factor de utilización — estiba mixta | C6: 0.92 | D6: grids puros lograron 96,1% (hig.) / 91,7% (facial)
A7: m³ útiles del contenedor | C7: =C5*C6 -> 70.288
A8: m³ útiles por cupo (÷ cupos) | C8: =C7/INPUTS!$C$14 -> 7.0288
A9: Cajas higiénico por cupo | C9: 66 | D9: el dial de composición
A10: m³ higiénico por cupo | C10: =C9*INPUTS!$C$18 -> 5.1282
A11: Cajas facial por cupo (calculado) | C11: =FLOOR((C8-C10)/INPUTS!$C$29,1) -> 32
A12: m³ usados por cupo | C12: =C10+C11*INPUTS!$C$29 -> 7.0162
A13: Holgura m³ por cupo | C13: =C8-C12 -> 0.0126
A14: kg por cupo | C14: =C9*INPUTS!$C$19+C11*INPUTS!$C$30 -> 950.6
A15: Composición del contenedor | C15: ="10 cupos · "&C9*10&" cajas higiénico + "&C11*10&" cajas facial" -> 10 cupos · 660 cajas higiénico + 320 cajas facial
A17: EL CUPO MIXTO — escenario base (markup INPUTS C33)
A18: Concepto | B18: Higiénico | C18: Facial | D18: Total cupo
A19: Cajas por cupo | B19: =C9 -> 66 | C19: =C11 -> 32 | D19: =B19+C19 -> 98
A20: Packs por cupo | B20: =B19*INPUTS!$C$12 -> 396 | C20: =C19*INPUTS!$C$25 -> 288 | D20: =B20+C20 -> 684
A21: Precio S/ /pack | B21: =INPUTS!$C$9*(1+INPUTS!$C$33) -> 22.4 | C21: =INPUTS!$C$22*(1+INPUTS!$C$33) -> 19.6
A22: Valor por cupo (S/) | B22: =B20*B21 -> 8870.4 | C22: =C20*C21 -> 5644.8 | D22: =B22+C22 -> 14515.2
A23: Costo por cupo (S/) | B23: =B20*INPUTS!$C$9 -> 6336 | C23: =C20*INPUTS!$C$22 -> 4032 | D23: =B23+C23 -> 10368
A24: Margen Wings por cupo (S/) | B24: =B22-B23 -> 2534.4 | C24: =C22-C23 -> 1612.8 | D24: =B24+C24 -> 4147.2
A25: Margen comprador S/ /pack | B25: =INPUTS!$C$10-B21 -> 7.6 | C25: =INPUTS!$C$23-C21 -> 5.4
A26: Margen comprador % s/ venta (retail base) | B26: =B25/INPUTS!$C$10 -> 0.25333333 | C26: =C25/INPUTS!$C$23 -> 0.216
A27: Margen comprador facial % (retail S/35) | C27: =(INPUTS!$C$31-C21)/INPUTS!$C$31 -> 0.44
A29: P&L CONTENEDOR MIXTO
A30: Ingreso 10 cupos (S/) | C30: =D22*10 -> 145152
A31: Costo 10 cupos (S/) | C31: =D23*10 -> 103680
A32: Margen bruto (S/) | C32: =C30-C31 -> 41472
A33: Margen bruto % s/ ingreso | C33: =C32/C30 -> 0.28571429
A34: Margen bruto (USD) | C34: =C32/INPUTS!$C$5 -> 11059.2
A36: Por qué existe esta hoja: el cupo mixto resuelve la rotación del facial —
A37: ~288 packs de facial por cupo (vs 1.062 en cupo puro) y le da al comprador surtido de góndola completo.

Sheet ESCALERA
A1: ESCALERA DE BENEFICIOS — higiénico, escenario base (INPUTS C33)
A3: Precio base S/ /pack | B3: =INPUTS!$C$9*(1+INPUTS!$C$33) -> 22.4
A4: Precio base por cupo | B4: =B3*INPUTS!$C$15 -> 12633.6
A6: Tier | B6: Cupos | C6: Descuento | D6: S/ /pack efectivo | E6: Precio por cupo (S/) | F6: Total pedido (S/) | G6: Total pedido (USD) | H6: Margen Wings S/ /pack | I6: Margen Wings % s/ costo | J6: Margen comprador S/ /pack | K6: Margen comprador % s/ venta
A7: CUPO | B7: 1 | C7: 0 | D7: =$B$3*(1-C7) -> 22.4 | E7: =D7*INPUTS!$C$15 -> 12633.6 | F7: =E7*B7 -> 12633.6 | G7: =F7/INPUTS!$C$5 -> 3368.96 | H7: =D7-INPUTS!$C$9 -> 6.4 | I7: =H7/INPUTS!$C$9 -> 0.4 | J7: =INPUTS!$C$10-D7 -> 7.6 | K7: =J7/INPUTS!$C$10 -> 0.25333333
A8: CUPO×3 | B8: 3 | C8: =INPUTS!$C$34 -> 0.03 | D8: =$B$3*(1-C8) -> 21.728 | E8: =D8*INPUTS!$C$15 -> 12254.592 | F8: =E8*B8 -> 36763.776 | G8: =F8/INPUTS!$C$5 -> 9803.6736 | H8: =D8-INPUTS!$C$9 -> 5.728 | I8: =H8/INPUTS!$C$9 -> 0.358 | J8: =INPUTS!$C$10-D8 -> 8.272 | K8: =J8/INPUTS!$C$10 -> 0.27573333
A9: MEDIO | B9: 5 | C9: =INPUTS!$C$35 -> 0.06 | D9: =$B$3*(1-C9) -> 21.056 | E9: =D9*INPUTS!$C$15 -> 11875.584 | F9: =E9*B9 -> 59377.92 | G9: =F9/INPUTS!$C$5 -> 15834.112 | H9: =D9-INPUTS!$C$9 -> 5.056 | I9: =H9/INPUTS!$C$9 -> 0.316 | J9: =INPUTS!$C$10-D9 -> 8.944 | K9: =J9/INPUTS!$C$10 -> 0.29813333
A10: CONTENEDOR | B10: 10 | C10: =INPUTS!$C$36 -> 0.08 | D10: =$B$3*(1-C10) -> 20.608 | E10: =D10*INPUTS!$C$15 -> 11622.912 | F10: =E10*B10 -> 116229.12 | G10: =F10/INPUTS!$C$5 -> 30994.432 | H10: =D10-INPUTS!$C$9 -> 4.608 | I10: =H10/INPUTS!$C$9 -> 0.288 | J10: =INPUTS!$C$10-D10 -> 9.392 | K10: =J10/INPUTS!$C$10 -> 0.31306667
A12: Crédito padrino por referido CONFIRMADO (se aplica al ciclo siguiente) | B12: =INPUTS!$C$37*$B$4 -> 252.672
A14: Los mismos % de escalera aplican a facial cuando su template se ratifique.

Sheet FLETE
A1: FLETE TACNA → DESTINO · por cupo de higiénico
A2: ⚠ Tarifas S/ /m³ son PLACEHOLDERS EDITABLES — reemplazar con cotizaciones reales de transportista.
A4: m³ por cupo | B4: =INPUTS!$C$13*INPUTS!$C$18 -> 7.3038
A5: kg por cupo | B5: =INPUTS!$C$13*INPUTS!$C$19 -> 911.8
A6: El papel cubica antes de pesar → la tarifa por m³ manda, no el kg.
A8: Ciudad | B8: km aprox | C8: Tarifa S/ /m³ (EDITABLE) | D8: Flete por cupo (S/) | E8: Flete por pack (S/) | F8: % del precio público | G8: Cupo entregado (S/)
A9: Moquegua | B9: 160 | C9: 35 | D9: =$B$4*C9 -> 255.633 | E9: =D9/INPUTS!$C$15 -> 0.45325 | F9: =E9/INPUTS!$C$10 -> 0.015108333 | G9: =ESCALERA!$B$4+D9 -> 12889.233
A10: Arequipa | B10: 370 | C10: 45 | D10: =$B$4*C10 -> 328.671 | E10: =D10/INPUTS!$C$15 -> 0.58275 | F10: =E10/INPUTS!$C$10 -> 0.019425 | G10: =ESCALERA!$B$4+D10 -> 12962.271
A11: Puno | B11: 380 | C11: 50 | D11: =$B$4*C11 -> 365.19 | E11: =D11/INPUTS!$C$15 -> 0.6475 | F11: =E11/INPUTS!$C$10 -> 0.021583333 | G11: =ESCALERA!$B$4+D11 -> 12998.79
A12: Juliaca | B12: 400 | C12: 52 | D12: =$B$4*C12 -> 379.7976 | E12: =D12/INPUTS!$C$15 -> 0.6734 | F12: =E12/INPUTS!$C$10 -> 0.022446667 | G12: =ESCALERA!$B$4+D12 -> 13013.398
A13: Cusco | B13: 790 | C13: 65 | D13: =$B$4*C13 -> 474.747 | E13: =D13/INPUTS!$C$15 -> 0.84175 | F13: =E13/INPUTS!$C$10 -> 0.028058333 | G13: =ESCALERA!$B$4+D13 -> 13108.347
A14: Lima | B14: 1290 | C14: 85 | D14: =$B$4*C14 -> 620.823 | E14: =D14/INPUTS!$C$15 -> 1.10075 | F14: =E14/INPUTS!$C$10 -> 0.036691667 | G14: =ESCALERA!$B$4+D14 -> 13254.423
A15: Trujillo | B15: 1850 | C15: 105 | D15: =$B$4*C15 -> 766.899 | E15: =D15/INPUTS!$C$15 -> 1.35975 | F15: =E15/INPUTS!$C$10 -> 0.045325 | G15: =ESCALERA!$B$4+D15 -> 13400.499
A16: Piura | B16: 2270 | C16: 120 | D16: =$B$4*C16 -> 876.456 | E16: =D16/INPUTS!$C$15 -> 1.554 | F16: =E16/INPUTS!$C$10 -> 0.0518 | G16: =ESCALERA!$B$4+D16 -> 13510.056
A18: Lectura: el flete por pack queda en céntimos → no justifica empaquetarlo en el precio del cupo.
A19: Recomendación S2 (mayoristas): precio EXW Tacna único + estimador de entrega transparente.
A20: Recomendación S1 (cadenas): cotizar entregado a su CD — las cadenas no compran EXW.

Sheet CONTENEDOR
A1: P&L POR CONTENEDOR — higiénico 40HC, escenario base (INPUTS C33)
A3: Costo total (945 cajas incl. holgura) | B3: =(INPUTS!$C$16+INPUTS!$C$17)*INPUTS!$C$12*INPUTS!$C$9 -> 90720
A4: Ingreso 10 cupos sin descuento | B4: =ESCALERA!$B$4*INPUTS!$C$14 -> 126336
A5: Margen bruto (S/) | B5: =B4-B3 -> 35616
A6: Margen bruto % s/ ingreso | B6: =B5/B4 -> 0.28191489
A7: Margen bruto (USD) | B7: =B5/INPUTS!$C$5 -> 9497.6
A9: ESCENARIOS DE MEZCLA DE TIERS
A10: Mezcla | B10: Ingreso (S/) | C10: Margen bruto (S/) | D10: % s/ ingreso
A11: 10 × CUPO (sin descuento) | B11: =ESCALERA!$E$7*10 -> 126336 | C11: =B11-$B$3 -> 35616 | D11: =C11/B11 -> 0.28191489
A12: 2×CUPO + 3×CUPO×3 + 5×MEDIO | B12: =2*ESCALERA!$E$7+3*ESCALERA!$E$8+5*ESCALERA!$E$9 -> 121408.9 | C12: =B12-$B$3 -> 30688.896 | D12: =C12/B12 -> 0.25277304
A13: 1 × CONTENEDOR dedicado | B13: =ESCALERA!$F$10 -> 116229.12 | C13: =B13-$B$3 -> 25509.12 | D13: =C13/B13 -> 0.21947271
A16: SENSIBILIDAD AL COSTO (precio publicado fijo, ingreso = mezcla 10×CUPO)
A17: Costo | B17: Costo total (S/) | C17: Margen bruto (S/) | D17: % s/ ingreso
A18: −10% | B18: =$B$3*0.9 -> 81648 | C18: =$B$11-B18 -> 44688 | D18: =C18/$B$11 -> 0.3537234
A19: base | B19: =$B$3*1 -> 90720 | C19: =$B$11-B19 -> 35616 | D19: =C19/$B$11 -> 0.28191489
A20: +10% | B20: =$B$3*1.1 -> 99792 | C20: =$B$11-B20 -> 26544 | D20: =C20/$B$11 -> 0.21010638
